fastcore/__init__.py
fastcore/_modidx.py
fastcore/all.py
fastcore/ansi.py
fastcore/basics.py
fastcore/dispatch.py
fastcore/docments.py
fastcore/docscrape.py
fastcore/foundation.py
fastcore/imghdr.py
fastcore/imports.py
fastcore/meta.py
fastcore/nb_imports.py
fastcore/net.py
fastcore/parallel.py
fastcore/py2pyi.py
fastcore/script.py
fastcore/shutil.py
fastcore/style.py
fastcore/test.py
fastcore/tools.py
fastcore/transform.py
fastcore/utils.py
fastcore/xdg.py
fastcore/xml.py
fastcore/xtras.py
fastcore-1.10.2.dist-info/licenses/LICENSE
fastcore-1.10.2.dist-info/METADATA
fastcore-1.10.2.dist-info/WHEEL
fastcore-1.10.2.dist-info/entry_points.txt
fastcore-1.10.2.dist-info/top_level.txt
fastcore-1.10.2.dist-info/RECORD
