Metadata-Version: 2.4
Name: fastcore
Version: 1.10.2
Summary: Python supercharged for fastai development
Home-page: https://github.com/AnswerDotAI/fastcore/
Author: Jeremy Howard and Sylvain Gugger
Author-email: infos@fast.ai
License: Apache Software License 2.0
Keywords: python
Classifier: Development Status :: 6 - Mature
Classifier: Intended Audience :: Developers
Classifier: License :: OSI Approved :: Apache Software License
Classifier: Natural Language :: English
Classifier: Programming Language :: Python :: 3.10
Classifier: Programming Language :: Python :: 3.11
Classifier: Programming Language :: Python :: 3.12
Classifier: Programming Language :: Python :: 3.13
Requires-Python: >=3.10
License-File: LICENSE
Requires-Dist: packaging
Provides-Extra: dev
Requires-Dist: numpy; extra == "dev"
Requires-Dist: nbdev>=0.2.39; extra == "dev"
Requires-Dist: matplotlib; extra == "dev"
Requires-Dist: pillow; extra == "dev"
Requires-Dist: torch; extra == "dev"
Requires-Dist: pandas; extra == "dev"
Requires-Dist: nbclassic; extra == "dev"
Requires-Dist: pysymbol_llm; extra == "dev"
Requires-Dist: llms-txt; extra == "dev"
Requires-Dist: plum-dispatch; extra == "dev"
Requires-Dist: toolslm; extra == "dev"
Dynamic: author
Dynamic: author-email
Dynamic: classifier
Dynamic: description
Dynamic: description-content-type
Dynamic: home-page
Dynamic: keywords
Dynamic: license
Dynamic: license-file
Dynamic: provides-extra
Dynamic: requires-dist
Dynamic: requires-python
Dynamic: summary
